README.rst
setup.py
nanostream/__init__.py
nanostream/civis_nodes.py
nanostream/node.py
nanostream.egg-info/PKG-INFO
nanostream.egg-info/SOURCES.txt
nanostream.egg-info/dependency_links.txt
nanostream.egg-info/requires.txt
nanostream.egg-info/top_level.txt
nanostream/bin/nanostream
nanostream/exp/__init__.py
nanostream/exp/import_hook.py
nanostream/exp/nanostream_encoder.py
nanostream/exp/nanostream_file_handler.py
nanostream/exp/nanostream_inner_join.py
nanostream/exp/nanostream_json_validator.py
nanostream/message/__init__.py
nanostream/message/batch.py
nanostream/message/canary.py
nanostream/message/message.py
nanostream/message/poison_pill.py
nanostream/message/trigger.py
nanostream/node_classes/__init__.py
nanostream/node_classes/civis_nodes.py
nanostream/node_classes/network_nodes.py
nanostream/node_queue/__init__.py
nanostream/node_queue/queue.py
nanostream/utils/__init__.py
nanostream/utils/data_structures.py
nanostream/utils/helpers.py
nanostream/utils/paginated_get_requests.py
nanostream/utils/required_arguments.py
nanostream/utils/set_attributes.py
nanostream/utils/treehorn.py
nanostream/watchdog/__init__.py
nanostream/watchdog/watchdog.py