Metadata-Version: 1.1
Name: nanostream
Version: 0.1.8
Summary: Small-scale stream processing for ETL
Home-page: https://github.com/zacernst/nanostream
Author: Zachary Ernst
Author-email: zac.ernst@gmail.com
License: UNKNOWN
Platform: UNKNOWN
Classifier: Programming Language :: Python :: 3
Classifier: License :: OSI Approved :: MIT License
Classifier: Operating System :: OS Independent
